rapidocr/__init__.py
rapidocr/config.yaml
rapidocr/default_models.yaml
rapidocr/main.py
rapidocr/cal_rec_boxes/__init__.py
rapidocr/cal_rec_boxes/main.py
rapidocr/ch_ppocr_cls/__init__.py
rapidocr/ch_ppocr_cls/main.py
rapidocr/ch_ppocr_cls/utils.py
rapidocr/ch_ppocr_det/__init__.py
rapidocr/ch_ppocr_det/main.py
rapidocr/ch_ppocr_det/utils.py
rapidocr/ch_ppocr_rec/__init__.py
rapidocr/ch_ppocr_rec/main.py
rapidocr/ch_ppocr_rec/utils.py
rapidocr/inference_engine/__init__.py
rapidocr/inference_engine/base.py
rapidocr/inference_engine/onnxruntime.py
rapidocr/inference_engine/openvino.py
rapidocr/inference_engine/paddlepaddle.py
rapidocr/inference_engine/torch.py
rapidocr/models/ch_PP-OCRv4_det_infer.onnx
rapidocr/models/ch_PP-OCRv4_rec_infer.onnx
rapidocr/models/ch_ppocr_mobile_v2.0_cls_infer.onnx
rapidocr/models/ppocr_keys_v1.txt
rapidocr/networks/__init__.py
rapidocr/networks/arch_config.yaml
rapidocr/networks/common.py
rapidocr/networks/architectures/__init__.py
rapidocr/networks/architectures/base_model.py
rapidocr/networks/backbones/__init__.py
rapidocr/networks/backbones/det_mobilenet_v3.py
rapidocr/networks/backbones/rec_hgnet.py
rapidocr/networks/backbones/rec_lcnetv3.py
rapidocr/networks/backbones/rec_mobilenet_v3.py
rapidocr/networks/backbones/rec_svtrnet.py
rapidocr/networks/heads/__init__.py
rapidocr/networks/heads/cls_head.py
rapidocr/networks/heads/det_db_head.py
rapidocr/networks/heads/rec_ctc_head.py
rapidocr/networks/heads/rec_multi_head.py
rapidocr/networks/necks/__init__.py
rapidocr/networks/necks/db_fpn.py
rapidocr/networks/necks/intracl.py
rapidocr/networks/necks/rnn.py
rapidocr/utils/__init__.py
rapidocr/utils/load_image.py
rapidocr/utils/logger.py
rapidocr/utils/parse_parameters.py
rapidocr/utils/process_img.py
rapidocr/utils/typings.py
rapidocr/utils/utils.py
rapidocr/utils/vis_res.py
ok_rapidocr_dml-0.0.7.dist-info/METADATA
ok_rapidocr_dml-0.0.7.dist-info/WHEEL
ok_rapidocr_dml-0.0.7.dist-info/entry_points.txt
ok_rapidocr_dml-0.0.7.dist-info/top_level.txt
ok_rapidocr_dml-0.0.7.dist-info/RECORD
